{
  "fecha_actualizacion": "2026-03-09",
  "dolar_bn": 1435.0,
  "total_registros": 3705,
  "total_estaciones": 1022,
  "precios_promedio": {
    "GNC": 730.9,
    "Gas Oil Grado 2": 1864.87,
    "Gas Oil Grado 3": 2075.92,
    "Nafta (premium) de más de 95 Ron": 2023.36,
    "Nafta (súper) entre 92 y 95 Ron": 1766.52
  },
  "variaciones_dia": {
    "GNC": 0.19,
    "Gas Oil Grado 2": 0.06,
    "Gas Oil Grado 3": 0.06,
    "Nafta (premium) de más de 95 Ron": 0.02,
    "Nafta (súper) entre 92 y 95 Ron": 0.05
  },
  "provincias_count": 24,
  "empresas_count": 9
}